modelforge/__init__.py
modelforge/__main__.py
modelforge/backends.py
modelforge/configuration.py
modelforge/environment.py
modelforge/gcs_backend.py
modelforge/http_.py
modelforge/index.py
modelforge/meta.py
modelforge/model.py
modelforge/models.py
modelforge/progress_bar.py
modelforge/registry.py
modelforge/slogging.py
modelforge/storage_backend.py
modelforge/tools.py
modelforge/version.py
modelforge/templates/meta.json
modelforge/templates/model.md.jinja2
modelforge/templates/readme.md.jinja2
modelforge-0.15.2.dist-info/LICENSE
modelforge-0.15.2.dist-info/METADATA
modelforge-0.15.2.dist-info/WHEEL
modelforge-0.15.2.dist-info/entry_points.txt
modelforge-0.15.2.dist-info/top_level.txt
modelforge-0.15.2.dist-info/RECORD
