Metadata-Version: 2.1
Name: modelforge
Version: 0.15.2
Summary: APIs and tools to work with abstract "models" - files with numpy arrays and metadata. It is possible to publish models, list them. There is a built-in cache. Storage has backends.
Home-page: https://github.com/src-d/modelforge
Author: source{d}
Author-email: machine-learning@sourced.tech
License: Apache 2.0
Download-URL: https://github.com/src-d/modelforge
Keywords: model,git,asdf,gcs,google cloud storage,machine learning,registry
Platform: UNKNOWN
Classifier: Development Status :: 3 - Alpha
Classifier: Environment :: Console
Classifier: Intended Audience :: Developers
Classifier: License :: OSI Approved :: Apache Software License
Classifier: Operating System :: POSIX
Classifier: Programming Language :: Python :: 3.4
Classifier: Programming Language :: Python :: 3.5
Classifier: Programming Language :: Python :: 3.6
Classifier: Programming Language :: Python :: 3.7
Classifier: Topic :: Software Development :: Libraries
Requires-Dist: asdf (<2.5,>=2.4.0)
Requires-Dist: lz4 (<3.0,>=1.0)
Requires-Dist: numpy (<2.0,>=1.12)
Requires-Dist: scipy (<2.0,>=1.0)
Requires-Dist: clint (<0.6,>=0.5.0)
Requires-Dist: google-cloud-storage (<=1.2.0,>=1.2)
Requires-Dist: urllib3 (<1.25)
Requires-Dist: requests (<3.0,>=2.0)
Requires-Dist: dulwich (<1.0,>=0.19)
Requires-Dist: jinja2 (<3.0,>=2.10.1)
Requires-Dist: humanize (<0.6,>=0.5.0)
Requires-Dist: python-dateutil (<3.0,>=2.0)
Requires-Dist: pygtrie (<3.0,>=1.0)
Requires-Dist: xxhash (<2.0,>=1.0)
Requires-Dist: spdx (<3.0,>=2.0)
Requires-Dist: typing ; python_version < "3.5"
